scheil/__init__.py
scheil/ordering.py
scheil/simulate.py
scheil/solidification_result.py
scheil/utils.py
scheil-0.3.0.dist-info/licenses/LICENSE
scheil-0.3.0.dist-info/METADATA
scheil-0.3.0.dist-info/WHEEL
scheil-0.3.0.dist-info/top_level.txt
scheil-0.3.0.dist-info/RECORD
