Metadata-Version: 2.4
Name: scheil
Version: 0.3.0
Summary: Scheil-Gulliver simulations using pycalphad.
Author-email: Brandon Bocklund <brandonbocklund@gmail.com>
License: MIT
Project-URL: Homepage, https://scheil.readthedocs.io
Classifier: Development Status :: 4 - Beta
Classifier: Intended Audience :: Science/Research
Classifier: Topic :: Scientific/Engineering :: Physics
Classifier: Topic :: Scientific/Engineering :: Chemistry
Classifier: License :: OSI Approved :: MIT License
Classifier: Programming Language :: Python :: 3
Requires-Python: >=3.11
License-File: LICENSE
Requires-Dist: numpy
Requires-Dist: pycalphad>=0.11.0
Requires-Dist: setuptools_scm[toml]>=6.0
Requires-Dist: scipy
Provides-Extra: dev
Requires-Dist: furo; extra == "dev"
Requires-Dist: ipython; extra == "dev"
Requires-Dist: pytest; extra == "dev"
Requires-Dist: sphinx; extra == "dev"
Requires-Dist: twine; extra == "dev"
Dynamic: license-file
